[
  {
    "name": "Người dùng facebook",
    "uid": "100070040388252",
    "time": "09:56:15 - 31/05/2025",
    "reason": "Đã tự động rời khỏi nhóm.",
    "facebook": "https://www.facebook.com/100070040388252"
  },
  {
    "name": "Nguyen Hoang Gia Nhi",
    "uid": "61572576922794",
    "time": "19:51:52 - 31/05/2025",
    "reason": "Đã tự động rời khỏi nhóm.",
    "facebook": "https://www.facebook.com/61572576922794"
  },
  {
    "name": "Tam Biet Doi",
    "uid": "61576193410824",
    "time": "10:12:50 - 02/06/2025",
    "reason": "Đã tự động rời khỏi nhóm.",
    "facebook": "https://www.facebook.com/61576193410824"
  },
  {
    "name": "Bo Quậy",
    "uid": "61575260575336",
    "time": "09:09:54 - 01/06/2025",
    "reason": "Đã bị Quản trị viên xóa khỏi nhóm.",
    "facebook": "https://www.facebook.com/61575260575336"
  },
  {
    "name": "Đăng Khôi",
    "uid": "61574767905355",
    "time": "09:10:05 - 01/06/2025",
    "reason": "Đã bị Quản trị viên xóa khỏi nhóm.",
    "facebook": "https://www.facebook.com/61574767905355"
  },
  {
    "name": "Lê Bé Pi",
    "uid": "61560889304623",
    "time": "06:34:05 - 02/06/2025",
    "reason": "Đã tự động rời khỏi nhóm.",
    "facebook": "https://www.facebook.com/61560889304623"
  },
  {
    "name": "Tấn Phát",
    "uid": "100092093242272",
    "time": "10:41:25 - 02/06/2025",
    "reason": "Đã tự động rời khỏi nhóm.",
    "facebook": "https://www.facebook.com/100092093242272"
  },
  {
    "name": "Võ Hải Yến",
    "uid": "100074612866502",
    "time": "18:25:50 - 05/06/2025",
    "reason": "Đã tự động rời khỏi nhóm.",
    "facebook": "https://www.facebook.com/100074612866502"
  }
]